maria_summarize_text_ai_assistant/__init__.py
maria_summarize_text_ai_assistant/summarize.py
maria_summarize_text_ai_assistant-0.1.6.dist-info/METADATA
maria_summarize_text_ai_assistant-0.1.6.dist-info/WHEEL
maria_summarize_text_ai_assistant-0.1.6.dist-info/top_level.txt
maria_summarize_text_ai_assistant-0.1.6.dist-info/RECORD
