Metadata-Version: 2.4
Name: maria_summarize_text_ai_assistant
Version: 0.1.6
Summary: A simple AI-powered text summarization helper using Groq API.
Author: Maria Jose
Requires-Dist: groq
Requires-Dist: python-dotenv
Dynamic: author
Dynamic: description
Dynamic: description-content-type
Dynamic: requires-dist
Dynamic: summary
